auto_logger/__init__.py
auto_logger/auto_logger.py
auto_logger/config.py
auto_logger/json_formatter.py
auto_logger/text_formatter.py
auto_logger-0.1.2.dist-info/WHEEL
auto_logger-0.1.2.dist-info/METADATA
auto_logger-0.1.2.dist-info/RECORD
