Metadata-Version: 2.1
Name: auto-logger
Version: 0.1.2
Summary: Automatically add function call logs and method call logs for Python code.
Home-page: https://github.com/duyixian1234/auto-logger
License: MIT
Author: duyixian
Author-email: duyixian1234@qq.com
Requires-Python: >=3.8,<4.0
Classifier: License :: OSI Approved :: MIT License
Classifier: Programming Language :: Python :: 3
Classifier: Programming Language :: Python :: 3.8
Classifier: Programming Language :: Python :: 3.9
Project-URL: Repository, https://github.com/duyixian1234/auto-logger
